proton_mail_bridge_client/__init__.py
proton_mail_bridge_client/client.py
proton_mail_bridge_client/config.py
proton_mail_bridge_client/connection.py
proton_mail_bridge_client/email.py
proton_mail_bridge_client/exceptions.py
proton_mail_bridge_client/folder.py
proton_mail_bridge_client/label.py
proton_mail_bridge_client/mcp_server.py
proton_mail_bridge_client/models.py
proton_mail_bridge_client/smtp_connection.py
proton_mail_bridge_client/utils.py
proton_mail_bridge_client-1.0.1.dist-info/licenses/LICENSE
proton_mail_bridge_client-1.0.1.dist-info/METADATA
proton_mail_bridge_client-1.0.1.dist-info/WHEEL
proton_mail_bridge_client-1.0.1.dist-info/entry_points.txt
proton_mail_bridge_client-1.0.1.dist-info/top_level.txt
proton_mail_bridge_client-1.0.1.dist-info/RECORD
