Metadata-Version: 2.4
Name: proton-mail-bridge-client
Version: 1.0.1
Summary: Easy-to-use Python library for managing ProtonMail via ProtonMail Bridge
Author: ProtonMail Bridge Client Contributors
License-Expression: LGPL-3.0-or-later
Keywords: protonmail,bridge,imap,email,automation
Classifier: Development Status :: 5 - Production/Stable
Classifier: Intended Audience :: Developers
Classifier: Programming Language :: Python :: 3
Classifier: Programming Language :: Python :: 3.12
Classifier: Programming Language :: Python :: 3.13
Classifier: Programming Language :: Python :: 3.14
Classifier: Topic :: Communications :: Email
Classifier: Topic :: Communications :: Email :: Email Clients (MUA)
Classifier: Topic :: Software Development :: Libraries :: Python Modules
Classifier: Operating System :: OS Independent
Classifier: Typing :: Typed
Requires-Python: <3.15,>=3.12
License-File: LICENSE
Requires-Dist: inscriptis>=2.7.0
Requires-Dist: mcp>=1.0.0
Provides-Extra: dev
Requires-Dist: pytest>=7.0; extra == "dev"
Requires-Dist: pytest-cov>=4.0; extra == "dev"
Dynamic: license-file
